qvtool/__init__.py
qvtool-0.0.1.dist-info/METADATA
qvtool-0.0.1.dist-info/RECORD
qvtool-0.0.1.dist-info/WHEEL
qvtool-0.0.1.dist-info/entry_points.txt
qvtool-0.0.1.dist-info/top_level.txt
