Metadata-Version: 2.1
Name: qvtool
Version: 0.0.1
Summary: open port of ipc
Home-page: UNKNOWN
Author: muxingMax
Author-email: log_e@qq.com
License: UNKNOWN
Platform: UNKNOWN
